Metadata-Version: 2.1
Name: smsru-sender
Version: 1.0.0
Summary: SMS.RU library
Home-page: https://github.com/egorgvo/smsru_sender.git
Author: Egor Gvo
Author-email: work.egvo@ya.ru
License: UNKNOWN
Platform: UNKNOWN
Classifier: Development Status :: 3 - Alpha
Classifier: Programming Language :: Python :: 3.8
Classifier: Intended Audience :: Developers
Classifier: Topic :: Software Development
Classifier: License :: OSI Approved :: MIT License
Classifier: Operating System :: OS Independent
Requires-Python: >=3.6
License-File: LICENSE.txt
